{
  "main": {
    "id": "132184c2ee3fd274",
    "type": "split",
    "children": [
      {
        "id": "63076156d3272c16",
        "type": "tabs",
        "children": [
          {
            "id": "0cda6d929ed31d97",
            "type": "leaf",
            "state": {
              "type": "markdown",
              "state": {
                "file": "Notes/all writings/API testing.md",
                "mode": "source",
                "source": false
              }
            }
          },
          {
            "id": "d9c11f518e20fca8",
            "type": "leaf",
            "state": {
              "type": "image",
              "state": {
                "file": "Notes/all writings/graphql-path-enum.png"
              }
            }
          },
          {
            "id": "ed9e2e247f73a266",
            "type": "leaf",
            "state": {
              "type": "markdown",
              "state": {
                "file": "Resources/Hacking API's.md",
                "mode": "source",
                "source": false
              }
            }
          },
          {
            "id": "946a43038211b3bf",
            "type": "leaf",
            "state": {
              "type": "markdown",
              "state": {
                "file": "Resources/Bug bounty bootcamp.md",
                "mode": "source",
                "source": false
              }
            }
          }
        ],
        "currentTab": 2
      }
    ],
    "direction": "vertical"
  },
  "left": {
    "id": "22df15993207541b",
    "type": "split",
    "children": [
      {
        "id": "7b51d872ac75ac6b",
        "type": "tabs",
        "children": [
          {
            "id": "a0768b61e94a56f7",
            "type": "leaf",
            "state": {
              "type": "search",
              "state": {
                "query": "",
                "matchingCase": false,
                "explainSearch": false,
                "collapseAll": false,
                "extraContext": false,
                "sortOrder": "alphabetical"
              }
            }
          },
          {
            "id": "5fafb9fd431b6cca",
            "type": "leaf",
            "state": {
              "type": "file-explorer",
              "state": {
                "sortOrder": "alphabetical"
              }
            }
          },
          {
            "id": "bc8b6f59076d7669",
            "type": "leaf",
            "state": {
              "type": "bookmarks",
              "state": {}
            }
          }
        ],
        "currentTab": 1
      }
    ],
    "direction": "horizontal",
    "width": 280.5,
    "collapsed": true
  },
  "right": {
    "id": "448bcc17a6b98769",
    "type": "split",
    "children": [
      {
        "id": "14d426d652e67d60",
        "type": "tabs",
        "children": [
          {
            "id": "1e0cd3c9e4d91c95",
            "type": "leaf",
            "state": {
              "type": "backlink",
              "state": {
                "file": "Resources/Hacking API's.md",
                "collapseAll": false,
                "extraContext": false,
                "sortOrder": "alphabetical",
                "showSearch": false,
                "searchQuery": "",
                "backlinkCollapsed": false,
                "unlinkedCollapsed": true
              }
            }
          },
          {
            "id": "08987c4f74b46537",
            "type": "leaf",
            "state": {
              "type": "outgoing-link",
              "state": {
                "file": "Resources/Hacking API's.md",
                "linksCollapsed": false,
                "unlinkedCollapsed": true
              }
            }
          },
          {
            "id": "87fc02f32f84eca0",
            "type": "leaf",
            "state": {
              "type": "tag",
              "state": {
                "sortOrder": "frequency",
                "useHierarchy": true
              }
            }
          },
          {
            "id": "511ce1da7fc3c464",
            "type": "leaf",
            "state": {
              "type": "outline",
              "state": {
                "file": "Resources/Hacking API's.md"
              }
            }
          },
          {
            "id": "d876f9d7c0e5f32f",
            "type": "leaf",
            "state": {
              "type": "BC-tree",
              "state": {}
            }
          },
          {
            "id": "7dfd1a2ee062c906",
            "type": "leaf",
            "state": {
              "type": "BC-matrix",
              "state": {}
            }
          }
        ]
      }
    ],
    "direction": "horizontal",
    "width": 300,
    "collapsed": true
  },
  "left-ribbon": {
    "hiddenItems": {
      "switcher:Open quick switcher": false,
      "graph:Open graph view": false,
      "canvas:Create new canvas": false,
      "daily-notes:Open today's daily note": false,
      "templates:Insert template": false,
      "command-palette:Open command palette": false,
      "breadcrumbs:Breadcrumbs Visualisation": false
    }
  },
  "active": "5fafb9fd431b6cca",
  "lastOpenFiles": [
    "Notes/all writings/API.md",
    "Notes/all writings/Amass.md",
    "Resources/Hacking API's.md",
    "Notes/all writings/RECON.md",
    "Resources/Bug bounty bootcamp.md",
    "Notes/all writings/API testing.md",
    "Notes/all writings/HTTP.md",
    "Notes/all writings/graphql-path-enum.png",
    "Notes/all writings/graphql voyager.png",
    "Notes/all writings/Payloads to insert.md",
    "API pentesting mindmap.png",
    "API pentesting mindmap graphql.png",
    "API pentesting mindmap attack.png",
    "Notes/Links.md",
    "Notes/all writings/GRAPHQL.md",
    "Resources/resource/how to use obsidian.md",
    "Resources/Links.md",
    "Notes/all writings",
    "Notes/all writing",
    "Notes/New folder",
    "Resources/resource/Writing.md",
    "Resources/resource/md cheatsheet.png",
    "Resources/resource/Report writing.md",
    "Resources/resource",
    "Resources/New folder",
    "Resources/how to use obsidian.md",
    "API testing/API testing.md",
    "Templates",
    "New folder",
    "Resources/Report writing.md",
    "Resources/md cheatsheet.png",
    "Resources/Writing.md",
    "Notes",
    "how to use obsidian and md.md",
    "alo.md",
    "Resources"
  ]
}